python_builder/__init__.py
python_builder/builder.py
python_builder/py.typed
python_builder-0.4.2.dist-info/LICENSE
python_builder-0.4.2.dist-info/METADATA
python_builder-0.4.2.dist-info/WHEEL
python_builder-0.4.2.dist-info/top_level.txt
python_builder-0.4.2.dist-info/RECORD
