Metadata-Version: 2.2
Name: python-builder
Version: 0.4.2
Summary: Implementation of generic python builder
Requires-Python: >=3.12
License-File: LICENSE
